LICENSE
MANIFEST.in
README.md
setup.py
tap_Kustomer/schemas/conversations.json
tap_Kustomer/schemas/customers.json
tap_Kustomer/schemas/kobjects.json
tap_Kustomer/schemas/messages.json
tap_Kustomer/schemas/notes.json
tap_Kustomer/schemas/shortcuts.json
tap_Kustomer/schemas/tags.json
tap_Kustomer/schemas/teams.json
tap_Kustomer/schemas/users.json
tap_kustomer/__init__.py
tap_kustomer/client.py
tap_kustomer/discover.py
tap_kustomer/error.py
tap_kustomer/schema.py
tap_kustomer/streams.py
tap_kustomer/sync.py
tap_kustomer/transform.py
tap_kustomer.egg-info/PKG-INFO
tap_kustomer.egg-info/SOURCES.txt
tap_kustomer.egg-info/dependency_links.txt
tap_kustomer.egg-info/entry_points.txt
tap_kustomer.egg-info/requires.txt
tap_kustomer.egg-info/top_level.txt
tap_kustomer/schemas/conversations.json
tap_kustomer/schemas/customers.json
tap_kustomer/schemas/kobjects.json
tap_kustomer/schemas/messages.json
tap_kustomer/schemas/notes.json
tap_kustomer/schemas/shortcuts.json
tap_kustomer/schemas/tags.json
tap_kustomer/schemas/teams.json
tap_kustomer/schemas/users.json
tap_kustomer/tests/denest_nodes_data.py
tap_kustomer/tests/stream_configs.py
tap_kustomer/tests/test_transform.py