Metadata-Version: 2.1
Name: tap-kustomer
Version: 1.0.1
Summary: Singer.io tap for extracting data from the Kustomer v1.0 API
Home-page: UNKNOWN
Author: scott.coleman@bytecode.io
License: UNKNOWN
Platform: UNKNOWN
Classifier: Programming Language :: Python :: 3 :: Only
Provides-Extra: dev
